[
  {
    "title": "Monitor AWS Credentials",
    "link": "https://medium.com/empathyco/how-to-monitor-the-age-of-your-aws-credentials-using-terraform-go-aws-lambda-and-slack-a9cc0ad322a",
    "description": "Published on Medium",
    "technology": "AWS, Terraform, Serverless",
    "featured": true
  },
  {
    "title": "Running Apache Flink on Kubernetes",
    "link": "https://medium.com/empathyco/running-apache-flink-on-kubernetes-10815a26559e",
    "description": "Published on Medium and DZone",
    "technology": "Flink, K8s",
    "featured": true
  },
  {
    "title": "Running Apache Spark on Kubernetes",
    "link": "https://medium.com/empathyco/running-apache-spark-on-kubernetes-2e64c73d0bb2",
    "description": "Published on Medium",
    "technology": "Apache Spark, K8s",
    "featured": true
  }
]
